rau/cli.py
rau/generation/__init__.py
rau/generation/beam_search.py
rau/generation/sample.py
rau/models/__init__.py
rau/models/common/shared_embeddings.py
rau/models/rnn/builtin.py
rau/models/rnn/language_model.py
rau/models/rnn/lstm.py
rau/models/rnn/simple_rnn.py
rau/models/transformer/common.py
rau/models/transformer/decoder.py
rau/models/transformer/encoder.py
rau/models/transformer/encoder_decoder.py
rau/models/transformer/input_layer.py
rau/models/transformer/mask.py
rau/models/transformer/positional_encodings.py
rau/models/transformer/unidirectional_encoder.py
rau/tasks/common/__init__.py
rau/tasks/common/command.py
rau/tasks/common/data.py
rau/tasks/common/data_preparation.py
rau/tasks/common/model.py
rau/tasks/common/training_loop.py
rau/tasks/language_modeling/batching.py
rau/tasks/language_modeling/data.py
rau/tasks/language_modeling/evaluate.py
rau/tasks/language_modeling/generate.py
rau/tasks/language_modeling/model.py
rau/tasks/language_modeling/prepare_data.py
rau/tasks/language_modeling/train.py
rau/tasks/language_modeling/training_loop.py
rau/tasks/language_modeling/vocabulary.py
rau/tasks/sequence_to_sequence/batching.py
rau/tasks/sequence_to_sequence/data.py
rau/tasks/sequence_to_sequence/model.py
rau/tasks/sequence_to_sequence/prepare_data.py
rau/tasks/sequence_to_sequence/train.py
rau/tasks/sequence_to_sequence/training_loop.py
rau/tasks/sequence_to_sequence/translate.py
rau/tasks/sequence_to_sequence/vocabulary.py
rau/tools/logging.py
rau/tools/ticker.py
rau/tools/torch/__init__.py
rau/tools/torch/compose.py
rau/tools/torch/embedding_layer.py
rau/tools/torch/init.py
rau/tools/torch/layer.py
rau/tools/torch/model_interface.py
rau/tools/torch/profile.py
rau/tools/torch/saver.py
rau/tools/torch/tied_linear.py
rau/training/early_stopping.py
rau/unidirectional/__init__.py
rau/unidirectional/composed.py
rau/unidirectional/dropout.py
rau/unidirectional/embedding.py
rau/unidirectional/output.py
rau/unidirectional/positional.py
rau-0.2.0.dist-info/LICENSE
rau-0.2.0.dist-info/METADATA
rau-0.2.0.dist-info/WHEEL
rau-0.2.0.dist-info/entry_points.txt
rau-0.2.0.dist-info/RECORD
