Metadata-Version: 2.3
Name: rau
Version: 0.2.0
Summary: Neural language modeling and sequence-to-sequence transduction in PyTorch.
License: MIT
Author: Brian DuSell
Author-email: brian.dusell@inf.ethz.ch
Requires-Python: >=3.11
Classifier: Intended Audience :: Developers
Classifier: Intended Audience :: Science/Research
Classifier: License :: OSI Approved :: MIT License
Classifier: Programming Language :: Python :: 3
Classifier: Programming Language :: Python :: 3.11
Classifier: Programming Language :: Python :: 3.12
Classifier: Programming Language :: Python :: 3.13
Classifier: Topic :: Scientific/Engineering :: Artificial Intelligence
Requires-Dist: humanfriendly (>=10.0,<11.0)
Requires-Dist: more-itertools (>=10.1.0,<11.0.0)
Requires-Dist: numpy (>=1.26.4,<2.0.0)
Requires-Dist: torch (>=2.1.0,<3.0.0)
Project-URL: Repository, https://github.com/bdusell/rau
